memoization/__init__.py
memoization/memoization.py
memoization/memoization.pyi
memoization/model.py
memoization/model.pyi
memoization/py.typed
memoization/backport/__init__.py
memoization/backport/backport_enum.py
memoization/caching/__init__.py
memoization/caching/fifo_cache.py
memoization/caching/fifo_cache.pyi
memoization/caching/lfu_cache.py
memoization/caching/lfu_cache.pyi
memoization/caching/lru_cache.py
memoization/caching/lru_cache.pyi
memoization/caching/plain_cache.py
memoization/caching/plain_cache.pyi
memoization/caching/statistic_cache.py
memoization/caching/statistic_cache.pyi
memoization/caching/general/__init__.py
memoization/caching/general/keys_order_dependent.py
memoization/caching/general/keys_order_dependent.pyi
memoization/caching/general/keys_order_independent.py
memoization/caching/general/keys_order_independent.pyi
memoization/caching/general/values_with_ttl.py
memoization/caching/general/values_with_ttl.pyi
memoization/caching/general/values_without_ttl.py
memoization/caching/general/values_without_ttl.pyi
memoization/config/__init__.py
memoization/config/algorithm_mapping.py
memoization/config/algorithm_mapping.pyi
memoization/constant/__init__.py
memoization/constant/flag.py
memoization/constant/flag.pyi
memoization/type/__init__.py
memoization/type/model.py
memoization/type/caching/__init__.py
memoization/type/caching/cache.py
memoization/type/caching/general/__init__.py
memoization/type/caching/general/keys.py
memoization/util/__init__.py
memoization/util/algorithm_extension_validator.py
memoization-0.3.2.dist-info/LICENSE
memoization-0.3.2.dist-info/METADATA
memoization-0.3.2.dist-info/WHEEL
memoization-0.3.2.dist-info/top_level.txt
memoization-0.3.2.dist-info/RECORD
