Metadata-Version: 2.1
Name: memoization
Version: 0.3.2
Summary: A powerful caching library for Python, with TTL support and multiple algorithm options. (https://github.com/lonelyenvoy/python-memoization)
Home-page: https://github.com/lonelyenvoy/python-memoization
Author: lonelyenvoy
Author-email: petrinchor@gmail.com
License: MIT
Keywords: memoization memorization remember decorator cache caching function callable functional ttl limited capacity fast high-performance optimization
Platform: UNKNOWN
Classifier: Development Status :: 5 - Production/Stable
Classifier: License :: OSI Approved :: MIT License
Classifier: Operating System :: OS Independent
Classifier: Programming Language :: Python :: 3.4
Classifier: Programming Language :: Python :: 3.5
Classifier: Programming Language :: Python :: 3.6
Classifier: Programming Language :: Python :: 3.7
Classifier: Programming Language :: Python :: 3.8
Classifier: Programming Language :: Python :: 3.9
Classifier: Topic :: Software Development :: Libraries
Classifier: Topic :: Software Development :: Libraries :: Python Modules
Requires-Python: >=3, !=3.0.*, !=3.1.*, !=3.2.*, !=3.3.*, <4
